ad1459/__init__.py
ad1459/__license__.py
ad1459/__version__.py
ad1459/application.py
ad1459/client.py
ad1459/commands.py
ad1459/formatting.py
ad1459/handlers.py
ad1459/network.py
ad1459/room.py
ad1459/testclient.py
ad1459/resources/in.donotspellitgav.ad1459.gresource
ad1459/widgets/__init__.py
ad1459/widgets/about.py
ad1459/widgets/headerbar.py
ad1459/widgets/irc_entry.py
ad1459/widgets/message.py
ad1459/widgets/message_buffer.py
ad1459/widgets/message_row.py
ad1459/widgets/right_click_menus.py
ad1459/widgets/room_row.py
ad1459/widgets/room_switcher.py
ad1459/widgets/server_popup.py
ad1459/widgets/topic.py
ad1459/widgets/user_row.py
ad1459/widgets/window.py
ad1459-1.19.0.data/scripts/ad1459
usr/share/applications/in.donotspellitgav.ad1459.desktop
usr/share/icons/hicolor/scalable/apps/in.donotspellitgav.Ad1459.Devel.svg
usr/share/icons/hicolor/scalable/apps/in.donotspellitgav.Ad1459.svg
usr/share/icons/hicolor/symbolic/apps/in.donotspellitgav.Ad1459-symbolic.svg
ad1459-1.19.0.dist-info/LICENSE
ad1459-1.19.0.dist-info/METADATA
ad1459-1.19.0.dist-info/WHEEL
ad1459-1.19.0.dist-info/top_level.txt
ad1459-1.19.0.dist-info/RECORD
